overdub/__init__.py
overdub/_version.py
overdub/bases.py
overdub/yaml.py
overdub-0.7.dist-info/DESCRIPTION.rst
overdub-0.7.dist-info/METADATA
overdub-0.7.dist-info/RECORD
overdub-0.7.dist-info/WHEEL
overdub-0.7.dist-info/metadata.json
overdub-0.7.dist-info/top_level.txt
