Metadata-Version: 2.0
Name: overdub
Version: 0.7
Summary: layered configuration aggregator
Home-page: http://py.errorist.io/overdub
Author: Xavier Barbosa
Author-email: clint.northwood@gmail.com
License: MIT
Keywords: configuration,layer,yaml
Platform: UNKNOWN
Classifier: Development Status :: 5 - Production/Stable
Classifier: Intended Audience :: Developers
Classifier: License :: OSI Approved :: MIT License
Classifier: Operating System :: OS Independent
Classifier: Programming Language :: Python
Classifier: Programming Language :: Python :: 2.7
Classifier: Programming Language :: Python :: 3
Classifier: Programming Language :: Python :: 3.3
Classifier: Programming Language :: Python :: 3.4
Classifier: Programming Language :: Python :: 3.5
Classifier: Topic :: Software Development :: Libraries
Classifier: Topic :: Software Development :: Libraries :: Python Modules
Provides-Extra: yaml
Requires-Dist: pyyaml; extra == 'yaml'
